setup.py
TracPermRedirect.egg-info/PKG-INFO
TracPermRedirect.egg-info/SOURCES.txt
TracPermRedirect.egg-info/dependency_links.txt
TracPermRedirect.egg-info/entry_points.txt
TracPermRedirect.egg-info/requires.txt
TracPermRedirect.egg-info/top_level.txt
permredirect/__init__.py
permredirect/filter.py