Metadata-Version: 1.0
Name: TracPermRedirect
Version: 3.0
Summary: Redirect users to the login screen on PermissionError.
Home-page: http://trac-hacks.org/wiki/PermRedirectPlugin
Author: Noah Kantrowitz
Author-email: noah@coderanger.net
License: BSD
Keywords: trac plugin
Platform: UNKNOWN
Classifier: Framework :: Trac
